pygatherer/__init__.py
pygatherer/py.typed
pygatherer/utils/__init__.py
pygatherer/utils/constants.py
pygatherer/utils/parser.py
pygatherer-0.7.0.dist-info/LICENSE.md
pygatherer-0.7.0.dist-info/METADATA
pygatherer-0.7.0.dist-info/WHEEL
pygatherer-0.7.0.dist-info/RECORD
