Metadata-Version: 2.3
Name: pygatherer
Version: 0.7.0
Summary: An API for the gatherer
Home-page: https://pygatherer.readthedocs.io/en/stable/
License: BSD-3-Clause
Keywords: MtG,magic
Author: Stephanos Kuma
Author-email: "Stephanos Kuma" <stephanos@kuma.ai>
Requires-Python: >=3.9
Classifier: Development Status :: 2 - Pre-Alpha
Classifier: Intended Audience :: Developers
Classifier: License :: OSI Approved :: BSD License
Classifier: Operating System :: OS Independent
Classifier: Programming Language :: Python :: 3 :: Only
Requires-Dist: beautifulsoup4 (~=4.0)
Requires-Dist: lxml (~=5.0)
Requires-Dist: pathurl (~=0.7)
Requires-Dist: requests (~=2.0)
Project-URL: Documentation, https://pygatherer.readthedocs.io/en/stable/
Project-URL: Repository, https://github.com/spapanik/pygatherer
